[
    {
        "map": "Unknown",
        "team1Rounds": 2,
        "team2Rounds": 3,
        "team1": [
            {
                "name": "DiogoFrancxssco",
                "operator": "Unknown",
                "elims": 39,
                "downs": 31,
                "assists": 12,
                "revives": 0,
                "damage": 4145,
                "captures": 7
            },
            {
                "name": "fifagomesg-19",
                "operator": "Unknown",
                "elims": 36,
                "downs": 21,
                "assists": 12,
                "revives": 1,
                "damage": 4291,
                "captures": 6
            },
            {
                "name": "miguel_paisana",
                "operator": "Unknown",
                "elims": 25,
                "downs": 12,
                "assists": 14,
                "revives": 2,
                "damage": 4039,
                "captures": 6
            },
            {
                "name": "franciscomrfe",
                "operator": "Unknown",
                "elims": 24,
                "downs": 20,
                "assists": 3,
                "revives": 0,
                "damage": 3749,
                "captures": 3
            }
        ],
        "team2": [
            {
                "name": "Gametti",
                "operator": "Unknown",
                "elims": 39,
                "downs": 34,
                "assists": 6,
                "revives": 4,
                "damage": 5497,
                "captures": 2
            },
            {
                "name": "pedro_jl76",
                "operator": "Unknown",
                "elims": 24,
                "downs": 11,
                "assists": 12,
                "revives": 2,
                "damage": 2875,
                "captures": 3
            },
            {
                "name": "tiagofranca6",
                "operator": "Unknown",
                "elims": 23,
                "downs": 15,
                "assists": 5,
                "revives": 1,
                "damage": 3037,
                "captures": 5
            },
            {
                "name": "antoniolamycp9",
                "operator": "Unknown",
                "elims": 21,
                "downs": 17,
                "assists": 5,
                "revives": 3,
                "damage": 3205,
                "captures": 5
            }
        ]
    },
    {
        "map": "Unknown",
        "team1Rounds": 3,
        "team2Rounds": 1,
        "team1": [
            {
                "name": "franciscomrfe",
                "operator": "Unknown",
                "elims": 35,
                "downs": 22,
                "assists": 13,
                "revives": 2,
                "damage": 4561,
                "captures": 3
            },
            {
                "name": "antoniolamycp9",
                "operator": "Unknown",
                "elims": 26,
                "downs": 19,
                "assists": 10,
                "revives": 2,
                "damage": 3064,
                "captures": 3
            },
            {
                "name": "martim1087",
                "operator": "Unknown",
                "elims": 18,
                "downs": 18,
                "assists": 2,
                "revives": 1,
                "damage": 2381,
                "captures": 1
            },
            {
                "name": "DiogoFrancxssco",
                "operator": "Unknown",
                "elims": 17,
                "downs": 13,
                "assists": 4,
                "revives": 1,
                "damage": 2305,
                "captures": 5
            }
        ],
        "team2": [
            {
                "name": "Gametti",
                "operator": "Unknown",
                "elims": 21,
                "downs": 19,
                "assists": 7,
                "revives": 2,
                "damage": 3467,
                "captures": 3
            },
            {
                "name": "tiagofranca6",
                "operator": "Unknown",
                "elims": 20,
                "downs": 14,
                "assists": 5,
                "revives": 1,
                "damage": 2885,
                "captures": 5
            },
            {
                "name": "Duarte_Sogalho",
                "operator": "Unknown",
                "elims": 15,
                "downs": 19,
                "assists": 1,
                "revives": 1,
                "damage": 2654,
                "captures": 2
            },
            {
                "name": "pedro_jl76",
                "operator": "Unknown",
                "elims": 13,
                "downs": 7,
                "assists": 3,
                "revives": 4,
                "damage": 1851,
                "captures": 3
            }
        ]
    },
    {
        "map": "Unknown",
        "team1Rounds": 3,
        "team2Rounds": 2,
        "team1": [
            {
                "name": "antoniolamycp9",
                "operator": "Unknown",
                "elims": 41,
                "downs": 28,
                "assists": 14,
                "revives": 0,
                "damage": 5933,
                "captures": 7
            },
            {
                "name": "franciscomrfe",
                "operator": "Unknown",
                "elims": 38,
                "downs": 32,
                "assists": 6,
                "revives": 2,
                "damage": 5707,
                "captures": 1
            },
            {
                "name": "DiogoFrancxssco",
                "operator": "Unknown",
                "elims": 28,
                "downs": 22,
                "assists": 9,
                "revives": 4,
                "damage": 3685,
                "captures": 3
            },
            {
                "name": "martim1087",
                "operator": "Unknown",
                "elims": 21,
                "downs": 11,
                "assists": 9,
                "revives": 3,
                "damage": 2666,
                "captures": 4
            }
        ],
        "team2": [
            {
                "name": "Gametti",
                "operator": "Unknown",
                "elims": 29,
                "downs": 27,
                "assists": 2,
                "revives": 6,
                "damage": 4267,
                "captures": 2
            },
            {
                "name": "tiagofranca6",
                "operator": "Unknown",
                "elims": 26,
                "downs": 24,
                "assists": 9,
                "revives": 2,
                "damage": 4824,
                "captures": 6
            },
            {
                "name": "pedro_jl76",
                "operator": "Unknown",
                "elims": 18,
                "downs": 6,
                "assists": 10,
                "revives": 0,
                "damage": 1842,
                "captures": 2
            },
            {
                "name": "Duarte_Sogalho",
                "operator": "Unknown",
                "elims": 15,
                "downs": 10,
                "assists": 5,
                "revives": 4,
                "damage": 2363,
                "captures": 1
            }
        ]
    },
    {
        "map": "Unknown",
        "team1Rounds": 3,
        "team2Rounds": 1,
        "team1": [
            {
                "name": "Gametti",
                "operator": "Unknown",
                "elims": 32,
                "downs": 23,
                "assists": 12,
                "revives": 5,
                "damage": 4542,
                "captures": 2
            },
            {
                "name": "tiagofranca6",
                "operator": "Unknown",
                "elims": 26,
                "downs": 19,
                "assists": 6,
                "revives": 3,
                "damage": 2924,
                "captures": 6
            },
            {
                "name": "Duarte_Sogalho",
                "operator": "Unknown",
                "elims": 20,
                "downs": 17,
                "assists": 4,
                "revives": 1,
                "damage": 2340,
                "captures": 3
            },
            {
                "name": "pedro_jl76",
                "operator": "Unknown",
                "elims": 18,
                "downs": 11,
                "assists": 8,
                "revives": 1,
                "damage": 2691,
                "captures": 1
            }
        ],
        "team2": [
            {
                "name": "franciscomrfe",
                "operator": "Unknown",
                "elims": 26,
                "downs": 21,
                "assists": 6,
                "revives": 1,
                "damage": 5033,
                "captures": 3
            },
            {
                "name": "antoniolamycp9",
                "operator": "Unknown",
                "elims": 19,
                "downs": 12,
                "assists": 7,
                "revives": 4,
                "damage": 2768,
                "captures": 5
            },
            {
                "name": "DiogoFrancxssco",
                "operator": "Unknown",
                "elims": 18,
                "downs": 17,
                "assists": 3,
                "revives": 1,
                "damage": 2850,
                "captures": 3
            },
            {
                "name": "martim1087",
                "operator": "Unknown",
                "elims": 16,
                "downs": 10,
                "assists": 3,
                "revives": 1,
                "damage": 2258,
                "captures": 3
            }
        ]
    },
    {
        "map": "Unknown",
        "team1Rounds": 1,
        "team2Rounds": 3,
        "team1": [
            {
                "name": "Gametti",
                "operator": "Unknown",
                "elims": 23,
                "downs": 15,
                "assists": 8,
                "revives": 2,
                "damage": 2410,
                "captures": 2
            },
            {
                "name": "tiagofranca6",
                "operator": "Unknown",
                "elims": 19,
                "downs": 12,
                "assists": 7,
                "revives": 4,
                "damage": 2533,
                "captures": 5
            },
            {
                "name": "Duarte_Sogalho",
                "operator": "Unknown",
                "elims": 19,
                "downs": 12,
                "assists": 7,
                "revives": 4,
                "damage": 2568,
                "captures": 2
            },
            {
                "name": "pedro_jl76",
                "operator": "Unknown",
                "elims": 15,
                "downs": 11,
                "assists": 6,
                "revives": 0,
                "damage": 2228,
                "captures": 5
            }
        ],
        "team2": [
            {
                "name": "DiogoFrancxssco",
                "operator": "Unknown",
                "elims": 31,
                "downs": 24,
                "assists": 7,
                "revives": 1,
                "damage": 4158,
                "captures": 3
            },
            {
                "name": "franciscomrfe",
                "operator": "Unknown",
                "elims": 31,
                "downs": 24,
                "assists": 15,
                "revives": 3,
                "damage": 4242,
                "captures": 4
            },
            {
                "name": "antoniolamycp9",
                "operator": "Unknown",
                "elims": 28,
                "downs": 22,
                "assists": 10,
                "revives": 0,
                "damage": 3585,
                "captures": 6
            },
            {
                "name": "martim1087",
                "operator": "Unknown",
                "elims": 13,
                "downs": 7,
                "assists": 9,
                "revives": 0,
                "damage": 1451,
                "captures": 2
            }
        ]
    },
    {
        "map": "Unknown",
        "team1Rounds": 3,
        "team2Rounds": 2,
        "team1": [
            {
                "name": "antoniolamycp9",
                "operator": "Unknown",
                "elims": 39,
                "downs": 24,
                "assists": 11,
                "revives": 5,
                "damage": 4592,
                "captures": 9
            },
            {
                "name": "Benny_Fuego",
                "operator": "Unknown",
                "elims": 32,
                "downs": 16,
                "assists": 16,
                "revives": 0,
                "damage": 3753,
                "captures": 5
            },
            {
                "name": "DiogoFrancxssco",
                "operator": "Unknown",
                "elims": 32,
                "downs": 25,
                "assists": 8,
                "revives": 3,
                "damage": 3474,
                "captures": 5
            },
            {
                "name": "Andre_santinho",
                "operator": "Unknown",
                "elims": 32,
                "downs": 19,
                "assists": 11,
                "revives": 2,
                "damage": 4875,
                "captures": 10
            }
        ],
        "team2": [
            {
                "name": "franciscomrfe",
                "operator": "Unknown",
                "elims": 37,
                "downs": 22,
                "assists": 20,
                "revives": 1,
                "damage": 5732,
                "captures": 4
            },
            {
                "name": "Gametti",
                "operator": "Unknown",
                "elims": 34,
                "downs": 26,
                "assists": 11,
                "revives": 4,
                "damage": 3802,
                "captures": 10
            },
            {
                "name": "tiagofranca6",
                "operator": "Unknown",
                "elims": 33,
                "downs": 23,
                "assists": 8,
                "revives": 3,
                "damage": 4645,
                "captures": 8
            },
            {
                "name": "martim1087",
                "operator": "Unknown",
                "elims": 20,
                "downs": 18,
                "assists": 4,
                "revives": 2,
                "damage": 2853,
                "captures": 5
            }
        ]
    }
]